CHANGELOG.rst
MANIFEST.in
README.rst
crsysapi.py
pyproject.toml
crsysapi.egg-info/PKG-INFO
crsysapi.egg-info/SOURCES.txt
crsysapi.egg-info/dependency_links.txt
crsysapi.egg-info/top_level.txt
test/test_crsysapi.py