Metadata-Version: 2.1
Name: crsysapi
Version: 6.22.1.post1
Summary: Python interface to CryptoSys API
Author: David Ireland, DI Management Services Pty Ltd
Project-URL: Homepage, https://www.cryptosys.net/api.html
Project-URL: Issues, https://www.cryptosys.net/contact/
Classifier: Programming Language :: Python :: 3
Requires-Python: >=3.6
